MANIFEST.in
README.md
cli.py
reqs.yaml
setup.cfg
setup.py
version.py
pyclk.egg-info/PKG-INFO
pyclk.egg-info/SOURCES.txt
pyclk.egg-info/dependency_links.txt
pyclk.egg-info/entry_points.txt
pyclk.egg-info/requires.txt
pyclk.egg-info/top_level.txt
src/__init__.py
src/commands/__init__.py
src/commands/activate.py
src/commands/build.py
src/commands/install.py
src/commands/purge.py
src/commands/run.py
src/utils/__init__.py
src/utils/chalk.py
src/utils/context.py
src/utils/dumper.py
src/utils/logger.py
src/utils/utils.py