Metadata-Version: 2.1
Name: pyclk
Version: 0.0.86
Summary: Python package to manage monorepo cli
Home-page: UNKNOWN
Author: Sebastian Tuyu
Author-email: contact@sebastiantuyu.com
License: MIT
Keywords: monorepo cli package manger
Platform: UNKNOWN
